sideeffect/__init__.py
sideeffect/main.py
sideeffect-1.0.4.dist-info/LICENSE
sideeffect-1.0.4.dist-info/METADATA
sideeffect-1.0.4.dist-info/WHEEL
sideeffect-1.0.4.dist-info/top_level.txt
sideeffect-1.0.4.dist-info/RECORD
