Metadata-Version: 2.1
Name: sideeffect
Version: 1.0.4
Summary: A Python library for managing state with synchronous or asynchronous side effects effortlessly.
Home-page: https://github.com/sharunashwanth/SideEffect
Author: Sharun Ashwanth K V
Maintainer: Sharun Ashwanth K V
Maintainer-email: sharunashwanth03@gmail.com
Keywords: sideeffect,state-management,reactivity
License-File: LICENSE
